LPLGather/__init__.py
LPLGather/parse.py
LPLGather/_config/__init__.py
LPLGather/_config/_config.py
LPLGather/_func/_func.py
LPLGather/_func/_utils.py
LPLGather/_schemas/__init__.py
LPLGather/_schemas/_schemas.py
LPLG-0.0.16.dist-info/LICENSE
LPLG-0.0.16.dist-info/METADATA
LPLG-0.0.16.dist-info/WHEEL
LPLG-0.0.16.dist-info/top_level.txt
LPLG-0.0.16.dist-info/RECORD
