Metadata-Version: 2.1
Name: LPLG
Version: 0.0.16
Summary: Gather date for LPL players
Author-email: Mateus Paulo <maatanalista@gmail.com>
Project-URL: Homepage, https://github.com/matpauloDS/LPLG
Project-URL: Bug Tracker, https://github.com/matpauloDS/LPLG/issues
Classifier: Programming Language :: Python :: 3
Classifier: License :: OSI Approved :: MIT License
Requires-Python: >=3.10
License-File: LICENSE
Requires-Dist: polars >=0.19.0
Requires-Dist: msgspec >=0.18.4
Requires-Dist: requests >=2.5.4.1
Requires-Dist: python-dotenv >=0.10.2
Requires-Dist: ruff >=0.1.5
Requires-Dist: numpy >=1.26.2
Requires-Dist: aiosonic >=0.17.0
